{"nodes": [{"id": "home_tunnel_dev_tunnel_backend_api_utils_response_py", "label": "response.py", "file_type": "code", "source_file": "api/utils/response.py", "source_location": "L1"}, {"id": "utils_response_single", "label": "single()", "file_type": "code", "source_file": "api/utils/response.py", "source_location": "L13"}, {"id": "any", "label": "Any", "file_type": "code", "source_file": "api/utils/response.py", "source_location": "L13"}, {"id": "utils_response_paginated", "label": "paginated()", "file_type": "code", "source_file": "api/utils/response.py", "source_location": "L23"}, {"id": "utils_response_referentiel", "label": "referentiel()", "file_type": "code", "source_file": "api/utils/response.py", "source_location": "L47"}, {"id": "utils_response_rationale_1", "label": "Helpers de normalisation des r\u00e9ponses API.  Trois formats standards : - single()", "file_type": "rationale", "source_file": "api/utils/response.py", "source_location": "L1"}, {"id": "utils_response_rationale_14", "label": "Retourne { data, audit? } pour un objet unique.", "file_type": "rationale", "source_file": "api/utils/response.py", "source_location": "L14"}, {"id": "utils_response_rationale_31", "label": "Retourne { items, pagination, facets?, audit? } pour une liste pagin\u00e9e.", "file_type": "rationale", "source_file": "api/utils/response.py", "source_location": "L31"}, {"id": "utils_response_rationale_48", "label": "Passe-travers explicite pour les listes plates de r\u00e9f\u00e9rentiel (statuts, types\u2026).", "file_type": "rationale", "source_file": "api/utils/response.py", "source_location": "L48"}], "edges": [{"source": "home_tunnel_dev_tunnel_backend_api_utils_response_py", "target": "typing", "relation": "imports_from", "context": "import", "confidence": "EXTRACTED", "source_file": "api/utils/response.py", "source_location": "L8", "weight": 1.0}, {"source": "home_tunnel_dev_tunnel_backend_api_utils_response_py", "target": "api_utils_pagination", "relation": "imports_from", "context": "import", "confidence": "EXTRACTED", "source_file": "api/utils/response.py", "source_location": "L10", "weight": 1.0}, {"source": "home_tunnel_dev_tunnel_backend_api_utils_response_py", "target": "utils_response_single", "relation": "contains", "confidence": "EXTRACTED", "source_file": "api/utils/response.py", "source_location": "L13", "weight": 1.0}, {"source": "utils_response_single", "target": "any", "relation": "references", "context": "parameter_type", "confidence": "EXTRACTED", "source_file": "api/utils/response.py", "source_location": "L13", "weight": 1.0}, {"source": "utils_response_single", "target": "any", "relation": "references", "context": "generic_arg", "confidence": "EXTRACTED", "source_file": "api/utils/response.py", "source_location": "L13", "weight": 1.0}, {"source": "home_tunnel_dev_tunnel_backend_api_utils_response_py", "target": "utils_response_paginated", "relation": "contains", "confidence": "EXTRACTED", "source_file": "api/utils/response.py", "source_location": "L23", "weight": 1.0}, {"source": "utils_response_paginated", "target": "any", "relation": "references", "context": "generic_arg", "confidence": "EXTRACTED", "source_file": "api/utils/response.py", "source_location": "L23", "weight": 1.0}, {"source": "utils_response_paginated", "target": "any", "relation": "references", "context": "generic_arg", "confidence": "EXTRACTED", "source_file": "api/utils/response.py", "source_location": "L23", "weight": 1.0}, {"source": "utils_response_paginated", "target": "any", "relation": "references", "context": "generic_arg", "confidence": "EXTRACTED", "source_file": "api/utils/response.py", "source_location": "L23", "weight": 1.0}, {"source": "home_tunnel_dev_tunnel_backend_api_utils_response_py", "target": "utils_response_referentiel", "relation": "contains", "confidence": "EXTRACTED", "source_file": "api/utils/response.py", "source_location": "L47", "weight": 1.0}, {"source": "utils_response_referentiel", "target": "any", "relation": "references", "context": "generic_arg", "confidence": "EXTRACTED", "source_file": "api/utils/response.py", "source_location": "L47", "weight": 1.0}, {"source": "utils_response_referentiel", "target": "any", "relation": "references", "context": "generic_arg", "confidence": "EXTRACTED", "source_file": "api/utils/response.py", "source_location": "L47", "weight": 1.0}, {"source": "utils_response_rationale_1", "target": "home_tunnel_dev_tunnel_backend_api_utils_response_py", "relation": "rationale_for", "confidence": "EXTRACTED", "source_file": "api/utils/response.py", "source_location": "L1", "weight": 1.0}, {"source": "utils_response_rationale_14", "target": "utils_response_single", "relation": "rationale_for", "confidence": "EXTRACTED", "source_file": "api/utils/response.py", "source_location": "L14", "weight": 1.0}, {"source": "utils_response_rationale_31", "target": "utils_response_paginated", "relation": "rationale_for", "confidence": "EXTRACTED", "source_file": "api/utils/response.py", "source_location": "L31", "weight": 1.0}, {"source": "utils_response_rationale_48", "target": "utils_response_referentiel", "relation": "rationale_for", "confidence": "EXTRACTED", "source_file": "api/utils/response.py", "source_location": "L48", "weight": 1.0}], "raw_calls": [{"caller_nid": "utils_response_single", "callee": "get_audit_rules", "is_member_call": false, "source_file": "/home/tunnel/DEV/tunnel-backend/api/utils/response.py", "source_location": "L19"}, {"caller_nid": "utils_response_paginated", "callee": "create_pagination_meta", "is_member_call": false, "source_file": "/home/tunnel/DEV/tunnel-backend/api/utils/response.py", "source_location": "L34"}, {"caller_nid": "utils_response_paginated", "callee": "get_audit_rules", "is_member_call": false, "source_file": "/home/tunnel/DEV/tunnel-backend/api/utils/response.py", "source_location": "L43"}]}